{
  "en": {
    "INVITATION": "You’ve been invited to join ?? on LiteFarm!",
    "CONFIRMATION": "You've successfully joined ?? !",
    "WITHHELD_CONSENT": "You didnt agree with the LiteFarm privacy policy – here are your options",
    "ACCESS_RESTORE": "Your access to ?? has been restored!",
    "ACCESS_REVOKE": "You've lost access to ?? on LiteFarm!",
    "WELCOME": "Welcome to LiteFarm!",
    "PASSWORD_RESET": "Password Reset Request",
    "PASSWORD_RESET_CONFIRMATION": "Your LiteFarm password has been changed",
    "HELP_REQUEST_EMAIL": "Your LiteFarm request for help"
  },
  "es": {
    "INVITATION": "Has sido invitado a unirte a ?? en LiteFarm!",
    "CONFIRMATION": "Te uniste exitosamente ?? !",
    "WITHHELD_CONSENT": "No aceptaste la politica de privacidad de Litefarm - estas son tus opciones",
    "ACCESS_RESTORE": "Tu acceso a ?? ha sido restaurado!",
    "ACCESS_REVOKE": "Has perdido acceso a ?? en LiteFarm!",
    "WELCOME": "Bienvenido a LiteFarm!",
    "PASSWORD_RESET": "Solicitud de recuperacion de clave",
    "PASSWORD_RESET_CONFIRMATION": "Tu clave en litefarm ha cambiado",
    "HELP_REQUEST_EMAIL": "Your LiteFarm request for help"
  },
  "pt": {
    "INVITATION": "You’ve been invited to join ?? on LiteFarm!",
    "CONFIRMATION": "You've successfully joined ?? !",
    "WITHHELD_CONSENT": "You didnt agree with the LiteFarm privacy policy – here are your options",
    "ACCESS_RESTORE": "Your access to ?? has been restored!",
    "ACCESS_REVOKE": "You've lost access to ?? on LiteFarm!",
    "WELCOME": "Welcome to LiteFarm!",
    "PASSWORD_RESET": "Password Reset Request",
    "PASSWORD_RESET_CONFIRMATION": "Your LiteFarm password has been changed",
    "HELP_REQUEST_EMAIL": "Your LiteFarm request for help"
  },
  "fr": {
    "INVITATION": "You’ve been invited to join ?? on LiteFarm!",
    "CONFIRMATION": "You've successfully joined ?? !",
    "WITHHELD_CONSENT": "You didnt agree with the LiteFarm privacy policy – here are your options",
    "ACCESS_RESTORE": "Your access to ?? has been restored!",
    "ACCESS_REVOKE": "You've lost access to ?? on LiteFarm!",
    "WELCOME": "Welcome to LiteFarm!",
    "PASSWORD_RESET": "Password Reset Request",
    "PASSWORD_RESET_CONFIRMATION": "Your LiteFarm password has been changed",
    "HELP_REQUEST_EMAIL": "Your LiteFarm request for help"
  }
}
